bmio/__init__.py
bmio/bmio.py
bmio/data_coerce.py
bmio/rcon_model/__init__.py
bmio/rcon_model/aimode_types.py
bmio/rcon_model/autoname.py
bmio/rcon_model/bot_difficulty_types.py
bmio/rcon_model/command_types.py
bmio/rcon_model/enemy_types.py
bmio/rcon_model/event_types.py
bmio/rcon_model/hat_types.py
bmio/rcon_model/mission_types.py
bmio/rcon_model/powerup_types.py
bmio/rcon_model/rcon_events.py
bmio/rcon_model/rcon_requests.py
bmio/rcon_model/request_cases.py
bmio/rcon_model/taunt_types.py
bmio/rcon_model/team_types.py
bmio/rcon_model/vice_types.py
bmio/rcon_model/weapon_types.py
bmio-0.2.0.dist-info/METADATA
bmio-0.2.0.dist-info/WHEEL
bmio-0.2.0.dist-info/top_level.txt
bmio-0.2.0.dist-info/RECORD
