Metadata-Version: 2.1
Name: bmio
Version: 0.2.0
Summary: Boring Man Rcon Scripting Library
Home-page: https://github.com/coyote963/bmio/
Author: coyote963
Author-email: coyoteandbird@gmail.com
Project-URL: Bug Tracker, https://github.com/coyote963/bmio/issues
Classifier: Programming Language :: Python :: 3
Classifier: License :: OSI Approved :: MIT License
Classifier: Operating System :: OS Independent
Requires-Python: >=3.6
Requires-Dist: loguru
